mf_pytorch/__init__.py
mf_pytorch/dataset.py
mf_pytorch-0.0.1.dist-info/LICENSE
mf_pytorch-0.0.1.dist-info/METADATA
mf_pytorch-0.0.1.dist-info/WHEEL
mf_pytorch-0.0.1.dist-info/top_level.txt
mf_pytorch-0.0.1.dist-info/RECORD
